legend/__init__.py
legend/delta.py
tests/__init__.py
tests/tests.py
legend_delta-0.1.10.dist-info/METADATA
legend_delta-0.1.10.dist-info/WHEEL
legend_delta-0.1.10.dist-info/top_level.txt
legend_delta-0.1.10.dist-info/RECORD
