Metadata-Version: 2.1
Name: legend-delta
Version: 0.1.10
Summary: This project helps organizations define Legend data models that can be converted into efficient Delta pipelines
Home-page: https://github.com/finos/legend-delta
Author: Antoine Amend
Author-email: antoine.amend@databricks.com
License: Apache License 2.0
Classifier: Programming Language :: Python :: 3
Classifier: License :: OSI Approved :: Apache Software License
Classifier: Operating System :: OS Independent
Provides-Extra: tests
Requires-Dist: pytest ; extra == 'tests'
